tnb_bill/__init__.py
tnb_bill/calculate.py
tnb_bill-0.2.dist-info/METADATA
tnb_bill-0.2.dist-info/WHEEL
tnb_bill-0.2.dist-info/top_level.txt
tnb_bill-0.2.dist-info/RECORD
