Metadata-Version: 2.1
Name: tnb_bill
Version: 0.2
Summary: A package to calculate electricity bills by TNB
Home-page: https://github.com/zhamri/tnb_bill
Author: zhamri
Author-email: zhamri@gmail.com
License: MIT
Classifier: Programming Language :: Python :: 3
Classifier: License :: OSI Approved :: MIT License
Classifier: Operating System :: OS Independent
Requires-Python: >=3.10
